lipomerge.py
lipomerge-0.1.1.dist-info/licenses/License.txt
lipomerge-0.1.1.dist-info/METADATA
lipomerge-0.1.1.dist-info/WHEEL
lipomerge-0.1.1.dist-info/entry_points.txt
lipomerge-0.1.1.dist-info/top_level.txt
lipomerge-0.1.1.dist-info/RECORD
