Metadata-Version: 2.4
Name: lipomerge
Version: 0.1.1
Summary: A tool to merge directories containing static libraries or other binaries into universal binaries.
Home-page: https://github.com/faaxm/lipomerge
Author: Falko Axmann
Classifier: Programming Language :: Python :: 3
Classifier: License :: OSI Approved :: GNU General Public License v3 (GPLv3)
Classifier: Operating System :: MacOS :: MacOS X
Requires-Python: >=3.6
License-File: License.txt
Dynamic: author
Dynamic: classifier
Dynamic: description
Dynamic: description-content-type
Dynamic: home-page
Dynamic: license-file
Dynamic: requires-python
Dynamic: summary
